<?xml version="1.0" encoding="euc-kr"?>
<query dynamic="true">
	<type>select</type>
	<description><![CDATA[]]></description>
	<reload>true</reload>
	<monitoring>true</monitoring>
	<result-count>0</result-count>
	<statement>
	SELECT COUNT(1) AS CNT
	  FROM SAPHEE.ZSDT0005 AS X  
	 WHERE X.MANDT = A.MANDT  
	   AND X.HOGI = #PJT#||#HNO#
	   AND X.CHARACTERISTIC = 'EL_EHM' 
FOR FETCH ONLY
WITH UR	</statement>
	<input default-name="ds_detail1">
	</input>
	<output default-name="ds_sdChk">
	</output>
</query>
